{
  "Version": 3,
  "Meta": {
    "Duration": 3.833,
    "Fps": 30.0,
    "Loop": true,
    "AreBeziersRestricted": true,
    "CurveCount": 140,
    "TotalSegmentCount": 758,
    "TotalPointCount": 1182,
    "UserDataCount": 2,
    "TotalUserDataSize": 21
  },
  "Curves": [
    {
      "Target": "Parameter",
      "Id": "ParamAngleX",
      "Segments": [
        0,
        0,
        1,
        0.1,
        0,
        0.2,
        -0.781,
        0.3,
        2.063,
        1,
        0.489,
        7.436,
        0.678,
        30,
        0.867,
        30,
        0,
        1.633,
        22.92,
        2,
        2.567,
        22.92,
        1,
        2.767,
        22.92,
        2.967,
        21.703,
        3.167,
        17.699,
        1,
        3.267,
        15.696,
        3.367,
        12.624,
        3.467,
        8.912,
        1,
        3.589,
        4.375,
        3.711,
        0,
        3.833,
        0
      ]
    },
    {
      "Target": "Parameter",
      "Id": "ParamAngleY",
      "Segments": [
        0,
        0,
        0,
        0.433,
        4.461,
        0,
        1.233,
        -16.24,
        0,
        1.933,
        -12.56,
        0,
        2.833,
        -21.52,
        1,
        2.966,
        -21.52,
        3.1,
        -21.947,
        3.233,
        -18.263,
        1,
        3.433,
        -12.736,
        3.633,
        0,
        3.833,
        0
      ]
    },
    {
      "Target": "Parameter",
      "Id": "ParamAngleZ",
      "Segments": [
        0,
        0,
        0,
        0.367,
        13,
        0,
        1.067,
        -7.2,
        0,
        1.767,
        11.514,
        1,
        2.078,
        11.514,
        2.389,
        10.628,
        2.7,
        6.795,
        1,
        3,
        3.099,
        3.3,
        -0.42,
        3.6,
        -0.42,
        1,
        3.678,
        -0.28,
        3.755,
        -0.14,
        3.833,
        0
      ]
    },
    {
      "Target": "Parameter",
      "Id": "ParamEyeLOpen",
      "Segments": [
        0,
        1,
        2,
        0.9,
        1,
        0,
        1.3,
        0,
        2,
        1.5,
        0,
        0,
        2,
        1,
        2,
        3,
        1,
        0,
        3.2,
        0,
        0,
        3.633,
        1,
        2,
        3.833,
        1
      ]
    },
    {
      "Target": "Parameter",
      "Id": "ParamEyeROpen",
      "Segments": [
        0,
        1,
        2,
        0.9,
        1,
        0,
        1.3,
        0,
        2,
        1.5,
        0,
        0,
        2,
        1,
        2,
        3,
        1,
        0,
        3.2,
        0,
        0,
        3.633,
        1,
        2,
        3.833,
        1
      ]
    },
    {
      "Target": "Parameter",
      "Id": "ParamEyeSmile",
      "Segments": [
        0,
        0,
        0,
        0.2,
        1,
        0,
        0.6,
        0.4,
        2,
        2.833,
        0.4,
        0,
        3.833,
        0
      ]
    },
    {
      "Target": "Parameter",
      "Id": "ParamEyeBallX",
      "Segments": [
        0,
        0,
        0,
        0.333,
        0.6,
        1,
        0.411,
        0.6,
        0.489,
        0.519,
        0.567,
        0.5,
        1,
        1.178,
        0.354,
        1.789,
        0.3,
        2.4,
        0.3,
        0,
        3.067,
        0.7,
        0,
        3.833,
        0
      ]
    },
    {
      "Target": "Parameter",
      "Id": "ParamEyeBallY",
      "Segments": [
        0,
        0,
        0,
        0.333,
        -0.3,
        2,
        0.567,
        -0.3,
        0,
        2.4,
        0.3,
        1,
        2.622,
        0.3,
        2.845,
        0.179,
        3.067,
        0.1,
        1,
        3.322,
        0.01,
        3.578,
        0,
        3.833,
        0
      ]
    },
    {
      "Target": "Parameter",
      "Id": "ParamMouthForm",
      "Segments": [
        0,
        0,
        0,
        0.333,
        -0.1,
        2,
        0.7,
        -0.1,
        0,
        0.767,
        0.1,
        0,
        1,
        -0.5,
        2,
        1.133,
        -0.5,
        0,
        1.267,
        0.2,
        1,
        1.334,
        0.2,
        1.4,
        0.049,
        1.467,
        -0.1,
        1,
        1.556,
        -0.299,
        1.644,
        -0.409,
        1.733,
        -0.6,
        1,
        1.811,
        -0.767,
        1.889,
        -0.9,
        1.967,
        -0.9,
        0,
        2.133,
        0.1,
        0,
        2.467,
        0,
        2,
        3.833,
        0
      ]
    },
    {
      "Target": "Parameter",
      "Id": "ParamMouthOpenY",
      "Segments": [
        0,
        0.3,
        0,
        0.333,
        0,
        2,
        0.7,
        0,
        1,
        0.722,
        0,
        0.745,
        0.288,
        0.767,
        0.3,
        1,
        0.845,
        0.342,
        0.922,
        0.358,
        1,
        0.4,
        1,
        1.022,
        0.412,
        1.045,
        0.7,
        1.067,
        0.7,
        1,
        1.089,
        0.7,
        1.111,
        0.486,
        1.133,
        0.4,
        1,
        1.178,
        0.229,
        1.222,
        0.2,
        1.267,
        0.2,
        1,
        1.334,
        0.2,
        1.4,
        0.56,
        1.467,
        0.8,
        1,
        1.5,
        0.92,
        1.534,
        0.9,
        1.567,
        0.9,
        0,
        1.733,
        0.6,
        1,
        1.811,
        0.6,
        1.889,
        0.602,
        1.967,
        0.7,
        1,
        2.022,
        0.77,
        2.078,
        1,
        2.133,
        1,
        1,
        2.155,
        1,
        2.178,
        0.433,
        2.2,
        0.361,
        1,
        2.289,
        0.071,
        2.378,
        0,
        2.467,
        0,
        2,
        2.533,
        0,
        0,
        3.833,
        0.3
      ]
    },
    {
      "Target": "Parameter",
      "Id": "ParamMouthX",
      "Segments": [
        0,
        0,
        0,
        0.767,
        0.4,
        1,
        0.845,
        0.4,
        0.922,
        -0.362,
        1,
        -0.9,
        1,
        1.022,
        -1,
        1.045,
        -1,
        1.067,
        -1,
        1,
        1.089,
        -1,
        1.111,
        -1,
        1.133,
        -0.9,
        1,
        1.178,
        -0.669,
        1.222,
        0.132,
        1.267,
        0.2,
        1,
        1.334,
        0.303,
        1.4,
        0.3,
        1.467,
        0.3,
        0,
        1.733,
        -1,
        2,
        1.967,
        -1,
        0,
        2.133,
        0.3,
        0,
        2.467,
        0,
        2,
        3.833,
        0
      ]
    },
    {
      "Target": "Parameter",
      "Id": "ParamBodyAngleX",
      "Segments": [
        0,
        0,
        0,
        0.267,
        -1.034,
        0,
        1.167,
        4,
        2,
        2.567,
        4,
        1,
        2.711,
        4,
        2.856,
        2.611,
        3,
        2.361,
        1,
        3.133,
        2.13,
        3.267,
        2.219,
        3.4,
        1.983,
        1,
        3.544,
        1.728,
        3.689,
        0,
        3.833,
        0
      ]
    },
    {
      "Target": "Parameter",
      "Id": "ParamBodyAngleY",
      "Segments": [
        0,
        0,
        0,
        0.3,
        3.774,
        0,
        0.833,
        -5.18,
        0,
        1.633,
        -0.556,
        0,
        2.567,
        -3.82,
        0,
        3.433,
        1.536,
        0,
        3.833,
        0
      ]
    },
    {
      "Target": "Parameter",
      "Id": "ParamBodyAngleZ",
      "Segments": [
        0,
        0,
        0,
        0.233,
        -0.734,
        1,
        0.422,
        -0.734,
        0.611,
        0.706,
        0.8,
        0.961,
        1,
        1.378,
        1.741,
        1.955,
        1.895,
        2.533,
        1.895,
        1,
        2.722,
        1.895,
        2.911,
        1.904,
        3.1,
        1.708,
        1,
        3.256,
        1.548,
        3.411,
        0.461,
        3.567,
        0.154,
        1,
        3.656,
        -0.022,
        3.744,
        0,
        3.833,
        0
      ]
    },
    {
      "Target": "Parameter",
      "Id": "Param4",
      "Segments": [
        0,
        0,
        0,
        0.2,
        8.192,
        0,
        0.667,
        -20,
        0,
        1.533,
        -12.4,
        0,
        2.4,
        -14.2,
        0,
        3.267,
        7.48,
        0,
        3.833,
        0
      ]
    },
    {
      "Target": "Parameter",
      "Id": "ParamHipY",
      "Segments": [
        0,
        0,
        0,
        0.333,
        -1.496,
        0,
        0.867,
        3.36,
        0,
        1.8,
        3.079,
        2,
        2.933,
        3.079,
        0,
        3.567,
        -0.325,
        0,
        3.833,
        0
      ]
    },
    {
      "Target": "Parameter",
      "Id": "ParamHipZ",
      "Segments": [
        0,
        0,
        1,
        0.233,
        0,
        0.467,
        0.392,
        0.7,
        0.669,
        1,
        1.278,
        1.354,
        1.855,
        1.561,
        2.433,
        1.561,
        0,
        3.1,
        -0.251,
        0,
        3.833,
        0
      ]
    },
    {
      "Target": "Parameter",
      "Id": "ParamLjian",
      "Segments": [
        0,
        0,
        0,
        0.3,
        3.948,
        0,
        0.767,
        -27,
        0,
        1.6,
        -8.26,
        0,
        2.5,
        -14,
        0,
        3.3,
        3.84,
        1,
        3.478,
        2.56,
        3.655,
        1.28,
        3.833,
        0
      ]
    },
    {
      "Target": "Parameter",
      "Id": "ParamArmL",
      "Segments": [
        0,
        0,
        0,
        0.367,
        4.717,
        1,
        0.522,
        4.717,
        0.678,
        -2.765,
        0.833,
        -3.86,
        1,
        1.266,
        -6.909,
        1.7,
        -7.449,
        2.133,
        -7.449,
        2,
        3.2,
        -7.449,
        0,
        3.6,
        0.869,
        0,
        3.833,
        0
      ]
    },
    {
      "Target": "Parameter",
      "Id": "ParamArmL1",
      "Segments": [
        0,
        0,
        0,
        0.4,
        3.071,
        1,
        0.622,
        3.071,
        0.845,
        0.19,
        1.067,
        -0.854,
        1,
        1.256,
        -1.741,
        1.444,
        -1.639,
        1.633,
        -1.639,
        2,
        2.6,
        -1.639,
        0,
        3,
        -4,
        0,
        3.467,
        3.071,
        0,
        3.833,
        0
      ]
    },
    {
      "Target": "Parameter",
      "Id": "ParamHandL",
      "Segments": [
        0,
        0,
        0,
        0.2,
        -7.003,
        1,
        0.278,
        -7.003,
        0.355,
        -5.54,
        0.433,
        -3.19,
        1,
        0.633,
        2.853,
        0.833,
        5.619,
        1.033,
        5.619,
        0,
        1.5,
        -3.19,
        2,
        2.333,
        -3.19,
        1,
        2.478,
        -3.19,
        2.622,
        -3.286,
        2.767,
        -6,
        1,
        2.922,
        -8.923,
        3.078,
        -14.035,
        3.233,
        -14.035,
        0,
        3.833,
        0
      ]
    },
    {
      "Target": "Parameter",
      "Id": "Paramshuke",
      "Segments": [
        0,
        0,
        0,
        0.3,
        30,
        0,
        0.667,
        -30,
        2,
        2.567,
        -30,
        1,
        2.634,
        -30,
        2.7,
        -30,
        2.767,
        -19.582,
        1,
        2.834,
        -8.531,
        2.9,
        30,
        2.967,
        30,
        0,
        3.333,
        0,
        2,
        3.833,
        0
      ]
    },
    {
      "Target": "Parameter",
      "Id": "Paramshuye",
      "Segments": [
        0,
        0,
        0,
        0.467,
        -30,
        0,
        0.867,
        30,
        0,
        1.333,
        -28.87,
        0,
        1.767,
        9.791,
        0,
        2.2,
        0,
        2,
        3.067,
        0,
        2,
        3.833,
        0
      ]
    },
    {
      "Target": "Parameter",
      "Id": "ParamRjian",
      "Segments": [
        0,
        0,
        0,
        0.233,
        -1,
        0,
        0.767,
        22,
        2,
        2.5,
        22,
        0,
        3.3,
        -6,
        0,
        3.833,
        0
      ]
    },
    {
      "Target": "Parameter",
      "Id": "ParamArmR",
      "Segments": [
        0,
        0,
        0,
        0.333,
        -7,
        0,
        0.9,
        30,
        0,
        1.667,
        17.22,
        0,
        2.6,
        30,
        1,
        2.744,
        30,
        2.889,
        29.843,
        3.033,
        25.854,
        1,
        3.2,
        21.251,
        3.366,
        4.772,
        3.533,
        1.548,
        1,
        3.633,
        -0.387,
        3.733,
        -0,
        3.833,
        0
      ]
    },
    {
      "Target": "Parameter",
      "Id": "ParamArmRY",
      "Segments": [
        0,
        0,
        0,
        1.033,
        12,
        0,
        1.733,
        -4.08,
        0,
        2.733,
        12,
        0,
        3.833,
        0
      ]
    },
    {
      "Target": "Parameter",
      "Id": "ParamArmR1",
      "Segments": [
        0,
        0,
        1,
        0.1,
        0,
        0.2,
        -0.322,
        0.3,
        1.381,
        1,
        0.456,
        4.03,
        0.611,
        18.657,
        0.767,
        22.138,
        1,
        0.856,
        24.127,
        0.944,
        24.46,
        1.033,
        25.52,
        1,
        1.289,
        28.568,
        1.544,
        30,
        1.8,
        30,
        1,
        2.111,
        30,
        2.422,
        28.034,
        2.733,
        25.52,
        1,
        2.911,
        24.083,
        3.089,
        24.163,
        3.267,
        22.138,
        1,
        3.456,
        19.986,
        3.644,
        0,
        3.833,
        0
      ]
    },
    {
      "Target": "Parameter",
      "Id": "ParamHandR",
      "Segments": [
        0,
        0,
        0,
        0.3,
        11,
        1,
        0.578,
        11,
        0.855,
        -3.781,
        1.133,
        -9.74,
        1,
        1.3,
        -13.315,
        1.466,
        -12.682,
        1.633,
        -12.682,
        1,
        1.722,
        -12.682,
        1.811,
        -12.708,
        1.9,
        -11.22,
        1,
        2.044,
        -8.802,
        2.189,
        -5.684,
        2.333,
        -5.684,
        1,
        2.5,
        -5.684,
        2.666,
        -11.816,
        2.833,
        -14.24,
        1,
        2.889,
        -15.048,
        2.944,
        -14.629,
        3,
        -15.188,
        1,
        3.078,
        -15.971,
        3.155,
        -18.556,
        3.233,
        -20.792,
        1,
        3.278,
        -22.07,
        3.322,
        -24.51,
        3.367,
        -26.933,
        1,
        3.389,
        -28.145,
        3.411,
        -30,
        3.433,
        -30,
        0,
        3.833,
        0
      ]
    },
    {
      "Target": "Parameter",
      "Id": "ParamHandR2",
      "Segments": [
        0,
        0,
        0,
        1.133,
        -27,
        2,
        2.833,
        -27,
        0,
        3.833,
        0
      ]
    },
    {
      "Target": "Parameter",
      "Id": "ParamFingerR",
      "Segments": [
        0,
        0,
        0,
        0.367,
        0.382,
        0,
        1.2,
        -0.243,
        0,
        2,
        0,
        0,
        2.867,
        -1,
        0,
        3.833,
        0
      ]
    },
    {
      "Target": "Parameter",
      "Id": "ParamFingerR6",
      "Segments": [
        0,
        0,
        0,
        0.433,
        0.4,
        0,
        1.267,
        -0.5,
        0,
        2.033,
        0.2,
        0,
        2.9,
        -0.3,
        0,
        3.833,
        0
      ]
    },
    {
      "Target": "Parameter",
      "Id": "ParamFingerR2",
      "Segments": [
        0,
        0,
        0,
        0.367,
        0.3,
        0,
        1.2,
        -0.3,
        0,
        2,
        0.2,
        0,
        2.867,
        -0.658,
        0,
        3.833,
        0
      ]
    },
    {
      "Target": "Parameter",
      "Id": "ParamFingerR7",
      "Segments": [
        0,
        0,
        0,
        0.433,
        0.4,
        0,
        1.267,
        -0.4,
        0,
        2.033,
        0.3,
        0,
        2.9,
        -0.2,
        0,
        3.833,
        0
      ]
    },
    {
      "Target": "Parameter",
      "Id": "ParamFingerR3",
      "Segments": [
        0,
        0,
        0,
        0.367,
        0.226,
        0,
        1.2,
        -0.165,
        0,
        2,
        0.209,
        0,
        2.867,
        -0.238,
        0,
        3.833,
        0
      ]
    },
    {
      "Target": "Parameter",
      "Id": "ParamFingerR8",
      "Segments": [
        0,
        0,
        0,
        0.433,
        0.262,
        0,
        1.267,
        -0.205,
        0,
        2.033,
        0.32,
        0,
        2.9,
        -0.16,
        0,
        3.833,
        0
      ]
    },
    {
      "Target": "Parameter",
      "Id": "ParamFingerR4",
      "Segments": [
        0,
        0,
        0,
        0.367,
        0.334,
        0,
        1.2,
        -0.157,
        0,
        2,
        0.323,
        0,
        2.867,
        -0.302,
        0,
        3.833,
        0
      ]
    },
    {
      "Target": "Parameter",
      "Id": "ParamFingerR9",
      "Segments": [
        0,
        0,
        0,
        0.433,
        0.618,
        0,
        1.267,
        -0.225,
        0,
        2.033,
        0.3,
        0,
        2.9,
        -0.403,
        0,
        3.833,
        0
      ]
    },
    {
      "Target": "Parameter",
      "Id": "ParamFingerR5",
      "Segments": [
        0,
        0,
        0,
        0.367,
        0.4,
        0,
        1.2,
        -0.187,
        0,
        2,
        0.236,
        0,
        2.867,
        -0.214,
        0,
        3.833,
        0
      ]
    },
    {
      "Target": "Parameter",
      "Id": "ParamFingerR10",
      "Segments": [
        0,
        0,
        0,
        0.433,
        0.3,
        0,
        1.267,
        -0.167,
        0,
        2.033,
        0.285,
        0,
        2.9,
        -0.251,
        0,
        3.833,
        0
      ]
    },
    {
      "Target": "Parameter",
      "Id": "ParamFingerR11",
      "Segments": [
        0,
        0,
        0,
        0.5,
        0.378,
        0,
        1.333,
        -0.232,
        0,
        2.067,
        0.205,
        0,
        2.967,
        -0.299,
        0,
        3.833,
        0
      ]
    },
    {
      "Target": "Parameter",
      "Id": "ParamLegLX",
      "Segments": [
        0,
        0,
        1,
        0.111,
        0,
        0.222,
        0.337,
        0.333,
        -2.068,
        1,
        0.478,
        -5.195,
        0.622,
        -16.62,
        0.767,
        -16.62,
        0,
        1.467,
        -9,
        0,
        2.5,
        -16.62,
        0,
        3.833,
        0
      ]
    },
    {
      "Target": "Parameter",
      "Id": "ParamLegLY",
      "Segments": [
        0,
        0,
        0,
        0.9,
        -9,
        0,
        1.7,
        -2.4,
        0,
        2.667,
        -9,
        0,
        3.833,
        0
      ]
    },
    {
      "Target": "Parameter",
      "Id": "Paramjiaobujiaoshui",
      "Segments": [
        0,
        1,
        2,
        0.5,
        1,
        0,
        0.7,
        0,
        2,
        3.167,
        0,
        0,
        3.833,
        1
      ]
    },
    {
      "Target": "Parameter",
      "Id": "ParamLegRX",
      "Segments": [
        0,
        0,
        0,
        0.767,
        3.06,
        2,
        2.5,
        3.06,
        0,
        3.833,
        0
      ]
    },
    {
      "Target": "Parameter",
      "Id": "ParamLegRY",
      "Segments": [
        0,
        0,
        0,
        0.767,
        5.64,
        2,
        2.5,
        5.64,
        0,
        3.833,
        0
      ]
    },
    {
      "Target": "Parameter",
      "Id": "Paramhudie1",
      "Segments": [
        0,
        0,
        0,
        0.3,
        30,
        0,
        0.5,
        -21,
        0,
        0.767,
        30,
        0,
        1.067,
        -19,
        0,
        1.533,
        30,
        0,
        2.067,
        -30,
        0,
        3.033,
        30,
        0,
        3.233,
        -21,
        0,
        3.467,
        30,
        0,
        3.833,
        0
      ]
    },
    {
      "Target": "Parameter",
      "Id": "Paramhudie2",
      "Segments": [
        0,
        -20.795,
        1,
        0.133,
        -20.795,
        0.267,
        -17.282,
        0.4,
        0,
        1,
        0.5,
        12.961,
        0.6,
        30,
        0.7,
        30,
        0,
        0.933,
        -21,
        0,
        1.167,
        30,
        0,
        1.467,
        -19,
        0,
        1.933,
        30,
        0,
        2.5,
        -30,
        1,
        2.711,
        -30,
        2.922,
        -23.815,
        3.133,
        0,
        1,
        3.233,
        11.281,
        3.333,
        30,
        3.433,
        30,
        0,
        3.633,
        -21,
        0,
        3.833,
        -20.795
      ]
    },
    {
      "Target": "Parameter",
      "Id": "Paramhudie3",
      "Segments": [
        0,
        30,
        0,
        0.533,
        -30,
        1,
        0.755,
        -30,
        0.978,
        -21.91,
        1.2,
        0,
        1,
        1.3,
        9.86,
        1.4,
        19,
        1.5,
        19,
        0,
        1.7,
        -14,
        0,
        1.933,
        13,
        0,
        2.267,
        -19,
        0,
        2.733,
        30,
        0,
        3.267,
        -30,
        0,
        3.833,
        30
      ]
    },
    {
      "Target": "Parameter",
      "Id": "Paramhudie4",
      "Segments": [
        0,
        0,
        0,
        0.667,
        -19,
        0,
        1.367,
        0,
        0,
        2.033,
        -22,
        0,
        2.733,
        0,
        0,
        3.4,
        -19,
        0,
        3.833,
        0
      ]
    },
    {
      "Target": "Parameter",
      "Id": "Paramyouxiuzi2a",
      "Segments": [
        0,
        0,
        0,
        0.367,
        27,
        0,
        0.833,
        0,
        0,
        1.467,
        27,
        0,
        1.8,
        0,
        0,
        2.167,
        27,
        0,
        2.633,
        0,
        0,
        3.267,
        27,
        0,
        3.833,
        0
      ]
    },
    {
      "Target": "Parameter",
      "Id": "Paramyouxiuzi2b",
      "Segments": [
        0,
        0,
        0,
        0.267,
        16,
        0,
        0.7,
        -4,
        0,
        1.267,
        16,
        0,
        1.8,
        0,
        0,
        2.067,
        16,
        0,
        2.5,
        -4,
        0,
        3.067,
        16,
        1,
        3.156,
        16,
        3.244,
        16.262,
        3.333,
        13.4,
        1,
        3.5,
        8.034,
        3.666,
        0,
        3.833,
        0
      ]
    },
    {
      "Target": "Parameter",
      "Id": "Paramyouxiuzi3a",
      "Segments": [
        0,
        0,
        0,
        0.367,
        -30,
        0,
        0.833,
        0,
        0,
        1.467,
        -30,
        0,
        1.8,
        0,
        0,
        2.167,
        -30,
        0,
        2.633,
        0,
        0,
        3.267,
        -30,
        0,
        3.833,
        0
      ]
    },
    {
      "Target": "Parameter",
      "Id": "Paramyouxiuzi3b",
      "Segments": [
        0,
        0,
        0,
        0.067,
        -14,
        0,
        0.5,
        19,
        1,
        0.633,
        19,
        0.767,
        -8.69,
        0.9,
        -14,
        1,
        1.078,
        -21.08,
        1.255,
        -21.297,
        1.433,
        -21.297,
        0,
        1.8,
        0,
        0,
        1.867,
        -14,
        0,
        2.3,
        19,
        1,
        2.433,
        19,
        2.567,
        -8.69,
        2.7,
        -14,
        1,
        2.878,
        -21.08,
        3.055,
        -21.297,
        3.233,
        -21.297,
        0,
        3.833,
        0
      ]
    },
    {
      "Target": "Parameter",
      "Id": "Paramyouxiuzi4a",
      "Segments": [
        0,
        0,
        0,
        0.167,
        14,
        0,
        0.6,
        -16,
        1,
        0.722,
        -16,
        0.845,
        -13.96,
        0.967,
        -4.593,
        1,
        1.134,
        8.18,
        1.3,
        18.791,
        1.467,
        18.791,
        0,
        1.8,
        0,
        0,
        1.967,
        14,
        0,
        2.4,
        -16,
        1,
        2.522,
        -16,
        2.645,
        -13.96,
        2.767,
        -4.593,
        1,
        2.934,
        8.18,
        3.1,
        18.791,
        3.267,
        18.791,
        0,
        3.833,
        0
      ]
    },
    {
      "Target": "Parameter",
      "Id": "Paramyouxiuzi4b",
      "Segments": [
        0,
        0,
        0,
        0.167,
        11,
        0,
        0.6,
        -6,
        0,
        1.1,
        11,
        0,
        1.8,
        0,
        0,
        1.967,
        11,
        0,
        2.4,
        -6,
        0,
        2.9,
        11,
        0,
        3.433,
        -14.703,
        0,
        3.833,
        0
      ]
    },
    {
      "Target": "Parameter",
      "Id": "ParamQianfaY",
      "Segments": [
        0,
        0,
        0,
        0.233,
        2.393,
        0,
        0.567,
        -7.739,
        0,
        1.1,
        4.52,
        0,
        1.633,
        -1.693,
        0,
        2.333,
        4.52,
        1,
        2.478,
        4.52,
        2.622,
        2.414,
        2.767,
        -0.573,
        1,
        2.9,
        -3.33,
        3.034,
        -4.242,
        3.167,
        -4.242,
        0,
        3.833,
        0
      ]
    },
    {
      "Target": "Parameter",
      "Id": "ParamHairFront",
      "Segments": [
        0,
        0,
        0,
        0.3,
        0.658,
        1,
        0.389,
        0.658,
        0.478,
        -0.327,
        0.567,
        -0.587,
        1,
        0.656,
        -0.847,
        0.744,
        -0.819,
        0.833,
        -0.819,
        0,
        1.167,
        0.898,
        0,
        1.533,
        0,
        0,
        1.8,
        0.7,
        1,
        1.889,
        0.7,
        1.978,
        0.281,
        2.067,
        -0.129,
        1,
        2.134,
        -0.437,
        2.2,
        -0.473,
        2.267,
        -0.473,
        1,
        2.345,
        -0.473,
        2.422,
        -0.053,
        2.5,
        0.315,
        1,
        2.589,
        0.735,
        2.678,
        0.815,
        2.767,
        0.815,
        0,
        3.467,
        -0.21,
        1,
        3.522,
        -0.21,
        3.578,
        -0.1,
        3.633,
        -0.055,
        1,
        3.7,
        -0.001,
        3.766,
        0,
        3.833,
        0
      ]
    },
    {
      "Target": "Parameter",
      "Id": "ParamHaiFrontY",
      "Segments": [
        0,
        0,
        0,
        0.4,
        0.271,
        0,
        0.533,
        -0.567,
        0,
        0.9,
        0.975,
        1,
        0.967,
        0.975,
        1.033,
        1,
        1.1,
        0.775,
        1,
        1.189,
        0.475,
        1.278,
        -0.161,
        1.367,
        -0.161,
        1,
        1.478,
        -0.161,
        1.589,
        -0.133,
        1.7,
        0,
        1,
        1.733,
        0.04,
        1.767,
        0.296,
        1.8,
        0.296,
        0,
        2.067,
        -0.115,
        0,
        2.5,
        0.815,
        1,
        2.589,
        0.815,
        2.678,
        0.826,
        2.767,
        0.615,
        1,
        2.9,
        0.298,
        3.034,
        -0.161,
        3.167,
        -0.161,
        1,
        3.234,
        -0.161,
        3.3,
        -0.02,
        3.367,
        0.181,
        1,
        3.445,
        0.415,
        3.522,
        0.5,
        3.6,
        0.5,
        0,
        3.833,
        0
      ]
    },
    {
      "Target": "Parameter",
      "Id": "ParamHairFront2",
      "Segments": [
        0,
        0,
        0,
        0.367,
        0.628,
        1,
        0.445,
        0.628,
        0.522,
        -0.289,
        0.6,
        -0.493,
        1,
        0.7,
        -0.755,
        0.8,
        -0.745,
        0.9,
        -0.745,
        0,
        1.167,
        0.975,
        0,
        1.667,
        -0.21,
        0,
        1.9,
        0.628,
        1,
        2,
        0.628,
        2.1,
        0.022,
        2.2,
        -0.318,
        1,
        2.256,
        -0.507,
        2.311,
        -0.473,
        2.367,
        -0.473,
        1,
        2.456,
        -0.473,
        2.544,
        -0.093,
        2.633,
        0.315,
        1,
        2.722,
        0.722,
        2.811,
        0.815,
        2.9,
        0.815,
        1,
        3.044,
        0.815,
        3.189,
        0.284,
        3.333,
        -0.055,
        1,
        3.411,
        -0.238,
        3.489,
        -0.21,
        3.567,
        -0.21,
        0,
        3.833,
        0
      ]
    },
    {
      "Target": "Parameter",
      "Id": "ParamHairFront2Y",
      "Segments": [
        0,
        0,
        0,
        0.467,
        0.181,
        0,
        0.633,
        -0.567,
        0,
        0.967,
        0.975,
        1,
        1.034,
        0.975,
        1.1,
        1,
        1.167,
        0.775,
        1,
        1.267,
        0.438,
        1.367,
        -0.161,
        1.467,
        -0.161,
        0,
        1.7,
        0.628,
        1,
        1.767,
        0.628,
        1.833,
        0.404,
        1.9,
        0.181,
        1,
        1.978,
        -0.079,
        2.055,
        -0.14,
        2.133,
        -0.14,
        0,
        2.633,
        0.815,
        1,
        2.722,
        0.815,
        2.811,
        0.827,
        2.9,
        0.615,
        1,
        3.022,
        0.322,
        3.145,
        -0.161,
        3.267,
        -0.161,
        1,
        3.345,
        -0.161,
        3.422,
        -0.056,
        3.5,
        0.181,
        1,
        3.567,
        0.384,
        3.633,
        0.5,
        3.7,
        0.5,
        0,
        3.833,
        0
      ]
    },
    {
      "Target": "Parameter",
      "Id": "ParamHairFront3",
      "Segments": [
        0,
        0,
        0,
        0.367,
        0.658,
        1,
        0.445,
        0.658,
        0.522,
        -0.628,
        0.6,
        -0.825,
        1,
        0.656,
        -0.966,
        0.711,
        -0.925,
        0.767,
        -0.925,
        1,
        0.822,
        -0.925,
        0.878,
        0.07,
        0.933,
        0.475,
        1,
        1,
        0.961,
        1.066,
        0.975,
        1.133,
        0.975,
        0,
        1.633,
        -0.21,
        1,
        1.655,
        -0.21,
        1.678,
        -0.151,
        1.7,
        0,
        1,
        1.767,
        0.454,
        1.833,
        0.7,
        1.9,
        0.7,
        1,
        1.978,
        0.7,
        2.055,
        -0.224,
        2.133,
        -0.373,
        1,
        2.2,
        -0.501,
        2.266,
        -0.473,
        2.333,
        -0.473,
        1,
        2.422,
        -0.473,
        2.511,
        -0.093,
        2.6,
        0.315,
        1,
        2.689,
        0.722,
        2.778,
        0.815,
        2.867,
        0.815,
        0,
        3.533,
        -0.21,
        1,
        3.589,
        -0.21,
        3.644,
        -0.121,
        3.7,
        -0.055,
        1,
        3.744,
        -0.002,
        3.789,
        0,
        3.833,
        0
      ]
    },
    {
      "Target": "Parameter",
      "Id": "ParamHairFront3Y",
      "Segments": [
        0,
        0,
        0,
        0.4,
        0.296,
        0,
        0.6,
        -0.567,
        0,
        0.933,
        0.975,
        1,
        1,
        0.975,
        1.066,
        1,
        1.133,
        0.775,
        1,
        1.233,
        0.438,
        1.333,
        -0.161,
        1.433,
        -0.161,
        1,
        1.522,
        -0.161,
        1.611,
        -0.144,
        1.7,
        0,
        1,
        1.767,
        0.108,
        1.833,
        0.296,
        1.9,
        0.296,
        0,
        2.133,
        -0.115,
        0,
        2.6,
        0.815,
        1,
        2.689,
        0.815,
        2.778,
        0.827,
        2.867,
        0.615,
        1,
        2.989,
        0.322,
        3.111,
        -0.161,
        3.233,
        -0.161,
        1,
        3.311,
        -0.161,
        3.389,
        -0.056,
        3.467,
        0.181,
        1,
        3.534,
        0.384,
        3.6,
        0.5,
        3.667,
        0.5,
        0,
        3.833,
        0
      ]
    },
    {
      "Target": "Parameter",
      "Id": "ParamHairSide",
      "Segments": [
        0,
        0,
        0,
        0.4,
        0.189,
        0,
        0.633,
        -0.731,
        1,
        0.689,
        -0.731,
        0.744,
        -0.753,
        0.8,
        -0.486,
        1,
        0.9,
        -0.006,
        1,
        0.63,
        1.1,
        0.63,
        1,
        1.189,
        0.63,
        1.278,
        -0.42,
        1.367,
        -0.589,
        1,
        1.445,
        -0.737,
        1.522,
        -0.706,
        1.6,
        -0.706,
        1,
        1.667,
        -0.706,
        1.733,
        -0.387,
        1.8,
        0,
        1,
        1.833,
        0.193,
        1.867,
        0.214,
        1.9,
        0.214,
        0,
        2.2,
        -0.706,
        1,
        2.267,
        -0.706,
        2.333,
        -0.727,
        2.4,
        -0.461,
        1,
        2.522,
        0.027,
        2.645,
        0.655,
        2.767,
        0.655,
        0,
        3.4,
        -0.706,
        1,
        3.478,
        -0.706,
        3.555,
        -0.535,
        3.633,
        -0.285,
        1,
        3.7,
        -0.071,
        3.766,
        0,
        3.833,
        0
      ]
    },
    {
      "Target": "Parameter",
      "Id": "ParamHairFrontY",
      "Segments": [
        0,
        0,
        0,
        0.467,
        0.356,
        1,
        0.5,
        0.356,
        0.534,
        0.357,
        0.567,
        0.039,
        1,
        0.611,
        -0.385,
        0.656,
        -1,
        0.7,
        -1,
        0,
        1.2,
        0.381,
        0,
        1.533,
        -0.173,
        1,
        1.622,
        -0.173,
        1.711,
        -0.159,
        1.8,
        0,
        1,
        1.856,
        0.099,
        1.911,
        0.381,
        1.967,
        0.381,
        1,
        2.011,
        0.381,
        2.056,
        0.294,
        2.1,
        0.064,
        1,
        2.233,
        -0.625,
        2.367,
        -1,
        2.5,
        -1,
        0,
        3,
        0.381,
        0,
        3.333,
        -0.173,
        0,
        3.6,
        0.26,
        0,
        3.833,
        0
      ]
    },
    {
      "Target": "Parameter",
      "Id": "ParamHairSide2",
      "Segments": [
        0,
        0,
        0,
        0.333,
        0.658,
        1,
        0.411,
        0.658,
        0.489,
        -0.561,
        0.567,
        -0.825,
        1,
        0.611,
        -0.976,
        0.656,
        -0.925,
        0.7,
        -0.925,
        1,
        0.767,
        -0.925,
        0.833,
        0.057,
        0.9,
        0.475,
        1,
        0.978,
        0.963,
        1.055,
        0.975,
        1.133,
        0.975,
        0,
        1.7,
        -0.21,
        1,
        1.733,
        -0.21,
        1.767,
        -0.203,
        1.8,
        0,
        1,
        1.856,
        0.339,
        1.911,
        0.7,
        1.967,
        0.7,
        1,
        2.011,
        0.7,
        2.056,
        -0.728,
        2.1,
        -0.8,
        1,
        2.167,
        -0.907,
        2.233,
        -0.9,
        2.3,
        -0.9,
        1,
        2.389,
        -0.9,
        2.478,
        -0.055,
        2.567,
        0.5,
        1,
        2.645,
        0.986,
        2.722,
        1,
        2.8,
        1,
        0,
        3.5,
        -0.21,
        1,
        3.556,
        -0.21,
        3.611,
        -0.109,
        3.667,
        -0.055,
        1,
        3.722,
        -0.001,
        3.778,
        0,
        3.833,
        0
      ]
    },
    {
      "Target": "Parameter",
      "Id": "ParamHairSide2y",
      "Segments": [
        0,
        0,
        0,
        0.533,
        0.271,
        0,
        0.633,
        -0.567,
        0,
        0.967,
        0.975,
        1,
        1.034,
        0.975,
        1.1,
        1,
        1.167,
        0.775,
        1,
        1.267,
        0.438,
        1.367,
        -0.161,
        1.467,
        -0.161,
        0,
        1.7,
        0.181,
        0,
        1.8,
        0,
        0,
        2.033,
        0.296,
        0,
        2.167,
        -0.542,
        0,
        2.633,
        1,
        1,
        2.722,
        1,
        2.811,
        1,
        2.9,
        0.8,
        1,
        3.022,
        0.488,
        3.145,
        -0.161,
        3.267,
        -0.161,
        1,
        3.345,
        -0.161,
        3.422,
        -0.056,
        3.5,
        0.181,
        1,
        3.567,
        0.384,
        3.633,
        0.5,
        3.7,
        0.5,
        0,
        3.833,
        0
      ]
    },
    {
      "Target": "Parameter",
      "Id": "ParamHairSide3",
      "Segments": [
        0,
        0,
        0,
        0.3,
        0.7,
        1,
        0.356,
        0.7,
        0.411,
        -0.676,
        0.467,
        -0.8,
        1,
        0.522,
        -0.924,
        0.578,
        -0.9,
        0.633,
        -0.9,
        1,
        0.722,
        -0.9,
        0.811,
        -0.589,
        0.9,
        0.044,
        1,
        0.989,
        0.677,
        1.078,
        1,
        1.167,
        1,
        0,
        1.8,
        0,
        0,
        2.1,
        0.7,
        1,
        2.178,
        0.7,
        2.255,
        0.037,
        2.333,
        -0.628,
        1,
        2.366,
        -0.913,
        2.4,
        -0.9,
        2.433,
        -0.9,
        1,
        2.522,
        -0.9,
        2.611,
        -0.589,
        2.7,
        0.044,
        1,
        2.789,
        0.677,
        2.878,
        1,
        2.967,
        1,
        0,
        3.633,
        -1,
        0,
        3.833,
        0
      ]
    },
    {
      "Target": "Parameter",
      "Id": "ParamHairSide2y2",
      "Segments": [
        0,
        0,
        0,
        0.2,
        0.296,
        0,
        0.333,
        -0.542,
        0,
        0.8,
        1,
        1,
        0.889,
        1,
        0.978,
        1,
        1.067,
        0.618,
        1,
        1.189,
        0.045,
        1.311,
        -1,
        1.433,
        -1,
        1,
        1.511,
        -1,
        1.589,
        -0.869,
        1.667,
        -0.566,
        1,
        1.711,
        -0.393,
        1.756,
        -0.15,
        1.8,
        0,
        1,
        1.867,
        0.224,
        1.933,
        0.296,
        2,
        0.296,
        0,
        2.133,
        -0.542,
        0,
        2.6,
        1,
        1,
        2.689,
        1,
        2.778,
        1,
        2.867,
        0.618,
        1,
        2.989,
        0.045,
        3.111,
        -1,
        3.233,
        -1,
        1,
        3.311,
        -1,
        3.389,
        -0.919,
        3.467,
        -0.566,
        1,
        3.534,
        -0.264,
        3.6,
        0.044,
        3.667,
        0.044,
        0,
        3.833,
        0
      ]
    },
    {
      "Target": "Parameter",
      "Id": "ParamHairBack",
      "Segments": [
        0,
        0,
        0,
        0.4,
        0.427,
        0,
        0.767,
        -0.9,
        1,
        0.845,
        -0.9,
        0.922,
        -0.341,
        1,
        0.044,
        1,
        1.1,
        0.539,
        1.2,
        0.615,
        1.3,
        0.615,
        0,
        1.8,
        0,
        0,
        2.2,
        0.427,
        0,
        2.567,
        -0.9,
        1,
        2.645,
        -0.9,
        2.722,
        -0.341,
        2.8,
        0.044,
        1,
        2.9,
        0.539,
        3,
        0.615,
        3.1,
        0.615,
        0,
        3.633,
        -0.427,
        0,
        3.833,
        0
      ]
    },
    {
      "Target": "Parameter",
      "Id": "ParamHairBackY",
      "Segments": [
        0,
        0,
        0,
        0.3,
        0.296,
        0,
        0.467,
        -0.542,
        0,
        0.9,
        1,
        1,
        0.989,
        1,
        1.078,
        1,
        1.167,
        0.618,
        1,
        1.289,
        0.045,
        1.411,
        -1,
        1.533,
        -1,
        1,
        1.622,
        -1,
        1.711,
        -0.268,
        1.8,
        0,
        1,
        1.9,
        0.302,
        2,
        0.296,
        2.1,
        0.296,
        0,
        2.267,
        -0.542,
        0,
        2.7,
        1,
        1,
        2.789,
        1,
        2.878,
        1,
        2.967,
        0.618,
        1,
        3.089,
        0.045,
        3.211,
        -1,
        3.333,
        -1,
        1,
        3.411,
        -1,
        3.489,
        -0.876,
        3.567,
        -0.566,
        1,
        3.656,
        -0.212,
        3.744,
        0,
        3.833,
        0
      ]
    },
    {
      "Target": "Parameter",
      "Id": "Parammaozi2a",
      "Segments": [
        0,
        0,
        0,
        0.1,
        3,
        0,
        0.7,
        -30,
        0,
        1.267,
        3,
        0,
        1.8,
        0,
        0,
        1.9,
        3,
        0,
        2.5,
        -30,
        0,
        3.067,
        3,
        0,
        3.833,
        0
      ]
    },
    {
      "Target": "Parameter",
      "Id": "Parammaozi2b",
      "Segments": [
        0,
        0,
        0,
        0.567,
        -30,
        0,
        1.167,
        0,
        2,
        1.8,
        0,
        0,
        2.367,
        -30,
        0,
        2.967,
        0,
        2,
        3.833,
        0
      ]
    },
    {
      "Target": "Parameter",
      "Id": "ParamClothes",
      "Segments": [
        0,
        0,
        0,
        0.233,
        -11,
        0,
        0.867,
        13,
        0,
        1.567,
        -11,
        0,
        1.8,
        0,
        0,
        2.033,
        -11,
        0,
        2.667,
        13,
        0,
        3.367,
        -11,
        0,
        3.833,
        0
      ]
    },
    {
      "Target": "Parameter",
      "Id": "ParamClothesY",
      "Segments": [
        0,
        0,
        0,
        0.233,
        -30,
        0,
        0.867,
        15,
        0,
        1.567,
        -30,
        0,
        1.8,
        0,
        0,
        2.033,
        -30,
        0,
        2.667,
        15,
        0,
        3.367,
        -30,
        0,
        3.833,
        0
      ]
    },
    {
      "Target": "Parameter",
      "Id": "ParamSkirt",
      "Segments": [
        0,
        0,
        0,
        0.5,
        -0.124,
        0,
        0.767,
        0.3,
        0,
        1.3,
        -0.992,
        0,
        1.8,
        0,
        0,
        2.3,
        -0.124,
        0,
        2.667,
        0.3,
        0,
        3.1,
        -0.992,
        0,
        3.833,
        0
      ]
    },
    {
      "Target": "Parameter",
      "Id": "ParamSkirtY",
      "Segments": [
        0,
        0,
        0,
        0.5,
        -0.303,
        0,
        0.767,
        1,
        0,
        1.3,
        -0.992,
        0,
        1.8,
        0,
        0,
        2.3,
        -0.303,
        0,
        2.667,
        1,
        0,
        3.1,
        -0.992,
        0,
        3.833,
        0
      ]
    },
    {
      "Target": "Parameter",
      "Id": "ParamSkirt2",
      "Segments": [
        0,
        0,
        0,
        0.567,
        0.503,
        0,
        0.867,
        -0.61,
        0,
        1.5,
        0.909,
        0,
        1.967,
        0,
        0,
        2.367,
        0.503,
        0,
        2.667,
        -0.61,
        0,
        3.5,
        1,
        0,
        3.833,
        0
      ]
    },
    {
      "Target": "Parameter",
      "Id": "ParamSkirt2Y",
      "Segments": [
        0,
        0,
        0,
        0.533,
        0.503,
        0,
        0.8,
        -0.5,
        0,
        1.267,
        1,
        0,
        1.8,
        0,
        0,
        2.333,
        0.503,
        0,
        2.6,
        -0.5,
        0,
        3.067,
        1,
        0,
        3.833,
        0
      ]
    },
    {
      "Target": "Parameter",
      "Id": "ParamSkirt3",
      "Segments": [
        0,
        0,
        0,
        0.533,
        0.503,
        0,
        0.867,
        -0.81,
        0,
        1.667,
        1,
        0,
        1.8,
        0,
        0,
        2.333,
        0.503,
        0,
        2.667,
        -0.81,
        0,
        3.467,
        1,
        0,
        3.833,
        0
      ]
    },
    {
      "Target": "Parameter",
      "Id": "ParamSkirt3Y",
      "Segments": [
        0,
        0,
        0,
        0.5,
        0.413,
        0,
        0.767,
        -0.6,
        0,
        1.2,
        1,
        0,
        1.8,
        0,
        0,
        2.3,
        0.413,
        0,
        2.567,
        -0.6,
        0,
        3,
        1,
        0,
        3.833,
        0
      ]
    },
    {
      "Target": "Parameter",
      "Id": "ParamSkirt4",
      "Segments": [
        0,
        0,
        0,
        0.533,
        0.458,
        0,
        0.867,
        -0.91,
        0,
        1.667,
        0.9,
        0,
        1.8,
        0,
        0,
        2.333,
        0.458,
        0,
        2.667,
        -0.91,
        0,
        3.467,
        0.9,
        0,
        3.833,
        0
      ]
    },
    {
      "Target": "Parameter",
      "Id": "ParamSkirt4Y",
      "Segments": [
        0,
        0,
        0,
        0.5,
        0.503,
        0,
        0.767,
        -0.4,
        0,
        1.2,
        1,
        0,
        1.8,
        0,
        0,
        2.3,
        0.503,
        0,
        2.567,
        -0.4,
        0,
        3,
        1,
        0,
        3.833,
        0
      ]
    },
    {
      "Target": "Parameter",
      "Id": "Paramhaiyanzhongxin",
      "Segments": [
        0,
        0,
        0,
        0.4,
        -26,
        0,
        0.8,
        18,
        0,
        1.267,
        -23,
        2,
        2.467,
        -23,
        0,
        2.8,
        0,
        2,
        3.833,
        0
      ]
    },
    {
      "Target": "Parameter",
      "Id": "ParamhaiyanshentiZ",
      "Segments": [
        0,
        0,
        0,
        0.467,
        5.06,
        0,
        1.1,
        -17,
        2,
        2.667,
        -17,
        0,
        3.3,
        0,
        2,
        3.833,
        0
      ]
    },
    {
      "Target": "Parameter",
      "Id": "Paramhaiyantou",
      "Segments": [
        0,
        0,
        2,
        0.333,
        0,
        0,
        0.6,
        7,
        0,
        1.167,
        -12,
        2,
        2.833,
        -12,
        0,
        3.1,
        0,
        2,
        3.833,
        0
      ]
    },
    {
      "Target": "Parameter",
      "Id": "ParamhaiyantouX",
      "Segments": [
        0,
        0,
        2,
        0.333,
        0,
        0,
        0.733,
        24,
        2,
        2.2,
        24,
        0,
        2.4,
        -10,
        2,
        2.933,
        -10,
        0,
        3.133,
        0,
        2,
        3.833,
        0
      ]
    },
    {
      "Target": "Parameter",
      "Id": "ParamhaiyantouY",
      "Segments": [
        0,
        0,
        2,
        0.333,
        0,
        0,
        0.633,
        -30,
        2,
        2.233,
        -30,
        0,
        2.5,
        24,
        1,
        2.622,
        24,
        2.745,
        23.02,
        2.867,
        16,
        1,
        2.945,
        11.533,
        3.022,
        0,
        3.1,
        0,
        2,
        3.833,
        0
      ]
    },
    {
      "Target": "Parameter",
      "Id": "Paramniaohuikaihe",
      "Segments": [
        0,
        0,
        2,
        1.1,
        0,
        0,
        1.2,
        17,
        0,
        1.333,
        0,
        2,
        1.467,
        0,
        0,
        1.633,
        30,
        0,
        1.767,
        0,
        2,
        2.433,
        0,
        0,
        2.533,
        30,
        2,
        2.567,
        30,
        0,
        2.7,
        0,
        2,
        3.833,
        0
      ]
    },
    {
      "Target": "Parameter",
      "Id": "Paramhaiyanweiba1",
      "Segments": [
        0,
        0,
        0,
        0.333,
        -6,
        0,
        1.667,
        28,
        0,
        3,
        -6,
        0,
        3.833,
        0
      ]
    },
    {
      "Target": "Parameter",
      "Id": "Paramhaiyanweiba1Y",
      "Segments": [
        0,
        0,
        0,
        1.333,
        30,
        1,
        1.778,
        30,
        2.222,
        0.11,
        2.667,
        0.042,
        1,
        3.056,
        -0.018,
        3.444,
        0,
        3.833,
        0
      ]
    },
    {
      "Target": "Model",
      "Id": "Opacity",
      "Segments": [
        0,
        1,
        0,
        3.833,
        1
      ]
    },
    {
      "Target": "Parameter",
      "Id": "ParamParamBrowLY",
      "Segments": [
        0,
        0,
        0,
        3.833,
        0
      ]
    },
    {
      "Target": "Parameter",
      "Id": "ParamParamBrowRY",
      "Segments": [
        0,
        0,
        0,
        3.833,
        0
      ]
    },
    {
      "Target": "Parameter",
      "Id": "ParamBrowLAngle",
      "Segments": [
        0,
        0,
        0,
        3.833,
        0
      ]
    },
    {
      "Target": "Parameter",
      "Id": "ParamBrowRAngle",
      "Segments": [
        0,
        0,
        0,
        3.833,
        0
      ]
    },
    {
      "Target": "Parameter",
      "Id": "ParamBrowLForm",
      "Segments": [
        0,
        0,
        0,
        3.833,
        0
      ]
    },
    {
      "Target": "Parameter",
      "Id": "ParamBrowRForm",
      "Segments": [
        0,
        0,
        0,
        3.833,
        0
      ]
    },
    {
      "Target": "Parameter",
      "Id": "ParamArmLY",
      "Segments": [
        0,
        0,
        0,
        3.833,
        0
      ]
    },
    {
      "Target": "Parameter",
      "Id": "ParamFingerL",
      "Segments": [
        0,
        0,
        0,
        3.833,
        0
      ]
    },
    {
      "Target": "Parameter",
      "Id": "ParamFingerL2",
      "Segments": [
        0,
        0,
        0,
        3.833,
        0
      ]
    },
    {
      "Target": "Parameter",
      "Id": "ParamFingerL6",
      "Segments": [
        0,
        0,
        0,
        3.833,
        0
      ]
    },
    {
      "Target": "Parameter",
      "Id": "ParamFingerL3",
      "Segments": [
        0,
        0,
        0,
        3.833,
        0
      ]
    },
    {
      "Target": "Parameter",
      "Id": "ParamFingerL7",
      "Segments": [
        0,
        0,
        0,
        3.833,
        0
      ]
    },
    {
      "Target": "Parameter",
      "Id": "ParamFingerL4",
      "Segments": [
        0,
        0,
        0,
        3.833,
        0
      ]
    },
    {
      "Target": "Parameter",
      "Id": "ParamFingerL8",
      "Segments": [
        0,
        0,
        0,
        3.833,
        0
      ]
    },
    {
      "Target": "Parameter",
      "Id": "ParamFingerL5",
      "Segments": [
        0,
        0,
        0,
        3.833,
        0
      ]
    },
    {
      "Target": "Parameter",
      "Id": "ParamFingerL9",
      "Segments": [
        0,
        0,
        0,
        3.833,
        0
      ]
    },
    {
      "Target": "Parameter",
      "Id": "ParamArmR1Y",
      "Segments": [
        0,
        0,
        0,
        3.833,
        0
      ]
    },
    {
      "Target": "Parameter",
      "Id": "ParamLegL",
      "Segments": [
        0,
        0,
        0,
        3.833,
        0
      ]
    },
    {
      "Target": "Parameter",
      "Id": "ParamLegL1",
      "Segments": [
        0,
        0,
        0,
        3.833,
        0
      ]
    },
    {
      "Target": "Parameter",
      "Id": "ParamFootL",
      "Segments": [
        0,
        0,
        0,
        3.833,
        0
      ]
    },
    {
      "Target": "Parameter",
      "Id": "ParamLegR",
      "Segments": [
        0,
        0,
        0,
        3.833,
        0
      ]
    },
    {
      "Target": "Parameter",
      "Id": "ParamLegR1",
      "Segments": [
        0,
        0,
        0,
        3.833,
        0
      ]
    },
    {
      "Target": "Parameter",
      "Id": "ParamFootR",
      "Segments": [
        0,
        0,
        0,
        3.833,
        0
      ]
    },
    {
      "Target": "Parameter",
      "Id": "Paramtuiqianhouqiehuan",
      "Segments": [
        0,
        0,
        0,
        3.833,
        0
      ]
    },
    {
      "Target": "Parameter",
      "Id": "ParamBlack1",
      "Segments": [
        0,
        0,
        0,
        3.833,
        0
      ]
    },
    {
      "Target": "Parameter",
      "Id": "ParamhaiyanqiejingZO",
      "Segments": [
        0,
        0,
        0,
        3.833,
        0
      ]
    },
    {
      "Target": "Parameter",
      "Id": "ParamhaiyanqiejingX2",
      "Segments": [
        0,
        0,
        0,
        3.833,
        0
      ]
    },
    {
      "Target": "Parameter",
      "Id": "ParamhaiyanqiejingY2",
      "Segments": [
        0,
        0,
        0,
        3.833,
        0
      ]
    },
    {
      "Target": "Parameter",
      "Id": "ParamBlack2",
      "Segments": [
        0,
        0,
        0,
        3.833,
        0
      ]
    },
    {
      "Target": "Parameter",
      "Id": "ParamBlack0",
      "Segments": [
        0,
        100,
        0,
        3.833,
        100
      ]
    },
    {
      "Target": "Parameter",
      "Id": "Paramkuangxianshikaiguan",
      "Segments": [
        0,
        0,
        0,
        3.833,
        0
      ]
    },
    {
      "Target": "Parameter",
      "Id": "Paramruhua",
      "Segments": [
        0,
        0,
        0,
        3.833,
        0
      ]
    },
    {
      "Target": "Parameter",
      "Id": "ParamHBX",
      "Segments": [
        0,
        0,
        0,
        3.833,
        0
      ]
    },
    {
      "Target": "Parameter",
      "Id": "ParamHBY2",
      "Segments": [
        0,
        0,
        0,
        3.833,
        0
      ]
    },
    {
      "Target": "Parameter",
      "Id": "ParamHBZ2",
      "Segments": [
        0,
        0,
        0,
        3.833,
        0
      ]
    },
    {
      "Target": "Parameter",
      "Id": "ParamHBO",
      "Segments": [
        0,
        0,
        0,
        3.833,
        0
      ]
    },
    {
      "Target": "Parameter",
      "Id": "ParamzhengtiX",
      "Segments": [
        0,
        0,
        0,
        3.833,
        0
      ]
    },
    {
      "Target": "Parameter",
      "Id": "ParamzhengtiY",
      "Segments": [
        0,
        0,
        0,
        3.833,
        0
      ]
    },
    {
      "Target": "Parameter",
      "Id": "ParamzhengtiZ",
      "Segments": [
        0,
        0,
        0,
        3.833,
        0
      ]
    },
    {
      "Target": "Parameter",
      "Id": "ParamzhengtiO",
      "Segments": [
        0,
        0,
        0,
        3.833,
        0
      ]
    },
    {
      "Target": "Parameter",
      "Id": "ParamhaiyanweiyiX",
      "Segments": [
        0,
        0,
        0,
        3.833,
        0
      ]
    },
    {
      "Target": "Parameter",
      "Id": "ParamhaiyanweiyiY",
      "Segments": [
        0,
        0,
        0,
        3.833,
        0
      ]
    },
    {
      "Target": "Parameter",
      "Id": "Paramhaiyanhuizhishunxu",
      "Segments": [
        0,
        0,
        0,
        3.833,
        0
      ]
    },
    {
      "Target": "Parameter",
      "Id": "Paramhainiaoxuanzhuan",
      "Segments": [
        0,
        0,
        0,
        3.833,
        0
      ]
    },
    {
      "Target": "Parameter",
      "Id": "Paramhaiyanyoujiao",
      "Segments": [
        0,
        0,
        0,
        3.833,
        0
      ]
    },
    {
      "Target": "Parameter",
      "Id": "Paramhaiyanzuojiao",
      "Segments": [
        0,
        0,
        0,
        3.833,
        0
      ]
    },
    {
      "Target": "Parameter",
      "Id": "Paramhaiyanqianchi1",
      "Segments": [
        0,
        0,
        0,
        3.833,
        0
      ]
    },
    {
      "Target": "Parameter",
      "Id": "Paramhaiyanqianchi2",
      "Segments": [
        0,
        0,
        0,
        3.833,
        0
      ]
    },
    {
      "Target": "Parameter",
      "Id": "Paramhaiyanchibangshandong",
      "Segments": [
        0,
        -30,
        0,
        3.833,
        -30
      ]
    }
  ],
  "UserData": [
    {
      "Time": 0.0,
      "Value": ""
    },
    {
      "Time": 0.77,
      "Value": "characterVoice_11_2.5"
    }
  ]
}